<templateSet group="user">
  <template name="::cb" value=".. code-block :: $END$" description="" toReformat="true" toShortenFQNames="true">
    <context>
      <option name="ANY_OPENAPI_JSON_FILE" value="false" />
      <option name="ANY_OPENAPI_YAML_FILE" value="false" />
      <option name="CSS" value="false" />
      <option name="CUCUMBER_FEATURE_FILE" value="false" />
      <option name="ECMAScript6" value="false" />
      <option name="GENERAL_JSON_FILE" value="false" />
      <option name="GENERAL_YAML_FILE" value="false" />
      <option name="HTML" value="false" />
      <option name="HTTP_CLIENT_ENVIRONMENT" value="false" />
      <option name="JAVA_SCRIPT" value="false" />
      <option name="JSON" value="false" />
      <option name="OTHER" value="true" />
      <option name="PHP" value="false" />
      <option name="REQUEST" value="false" />
      <option name="SHELL_SCRIPT" value="false" />
      <option name="SQL" value="false" />
      <option name="Twig" value="false" />
      <option name="TypeScript" value="false" />
      <option name="XML" value="false" />
    </context>
  </template>
  <template name="dv" value="die(var_dump(__METHOD__.':'.__LINE__));" description="die(var_dump());" toReformat="false" toShortenFQNames="true">
    <context>
      <option name="PHP" value="true" />
    </context>
  </template>
</templateSet>